setup.cfg
setup.py
transactions/__init__.py
transactions/transactions.py
transactions/utils.py
transactions.egg-info/PKG-INFO
transactions.egg-info/SOURCES.txt
transactions.egg-info/dependency_links.txt
transactions.egg-info/requires.txt
transactions.egg-info/top_level.txt
transactions/services/__init__.py
transactions/services/blockrservice.py
transactions/services/daemonservice.py
transactions/services/exceptions.py
transactions/services/service.py