Metadata-Version: 1.1
Name: transactions
Version: 0.1.0
Summary: transactions: Bitcoin for Humans
Home-page: https://github.com/ascribe/transactions
Author: Rodolphe Marques
Author-email: rodolphe@ascribe.io
License: Apache Software License
Platform: UNKNOWN
Classifier: Development Status :: 3 - Alpha
Classifier: Intended Audience :: Developers
Classifier: Natural Language :: English
Classifier: License :: OSI Approved :: Apache Software License
Classifier: Programming Language :: Python :: 2
Classifier: Programming Language :: Python :: 2.7
Classifier: Topic :: Software Development
